__init__.py
linux.py
mactalk.py
unisapi.py
unispeak.py
unispeak_nvda.py
unispeak-1.1.dist-info/LICENSE
unispeak-1.1.dist-info/METADATA
unispeak-1.1.dist-info/WHEEL
unispeak-1.1.dist-info/top_level.txt
unispeak-1.1.dist-info/RECORD
