Metadata-Version: 2.1
Name: unispeak
Version: 1.1
Summary: adds speech capabilities, nvda, NSS, sapi.
License-File: LICENSE
